{
  "nodes": [
    {
      "id": "node1",
      "shape": "重点",
      "label": "常打雷",
      "personId": "12123"
    },
    {
      "id": "node2",
      "label": "张美丽",
      "shape": "非重点",
      "personId": ""
    },
    {
      "id": "node3",
      "label": "张靓男",
      "shape": "非重点",
      "personId": ""
    },
    {
      "id": "node4",
      "label": "常遇春",
      "shape": "非重点",
      "personId": ""
    }
  ],
  "edges": [
    {
      "target": "node4",
      "source": "node1",
      "label": "堂弟",
      "shape": "亲属"
    },
    {
      "target": "node3",
      "source": "node1",
      "label": "表弟",
      "shape": "亲属"
    },
    {
      "target": "node2",
      "source": "node1",
      "label": "妻子",
      "shape": "亲属"
    }
  ]
}